shodankey/__init__.py
shodankey/core.py
shodankey-1.0.0.dist-info/METADATA
shodankey-1.0.0.dist-info/WHEEL
shodankey-1.0.0.dist-info/top_level.txt
shodankey-1.0.0.dist-info/RECORD
