Metadata-Version: 2.1
Name: shodankey
Version: 1.0.0
Summary: A package to validate and retrieve information from the Shodan API
Home-page: https://github.com/ByteBreach/shodankey
Author: Fidal
Author-email: mrfidal@proton.me
Keywords: shodan,MrFidal,api,security,network-scanning,information-gathering,api-key-validation
Classifier: Development Status :: 4 - Beta
Classifier: Intended Audience :: Developers
Classifier: Intended Audience :: Information Technology
Classifier: Topic :: Security
Classifier: Programming Language :: Python :: 3
Classifier: Programming Language :: Python :: 3.6
Classifier: Programming Language :: Python :: 3.7
Classifier: Programming Language :: Python :: 3.8
Classifier: Programming Language :: Python :: 3.9
Classifier: License :: OSI Approved :: MIT License
Classifier: Operating System :: OS Independent
Requires-Python: >=3.6
Requires-Dist: requests
